XPT2046_asukiaaa_python/__init__.py
XPT2046_asukiaaa_python/xpt2046.py
XPT2046_asukiaaa_python-1.0.0.dist-info/LICENSE
XPT2046_asukiaaa_python-1.0.0.dist-info/METADATA
XPT2046_asukiaaa_python-1.0.0.dist-info/WHEEL
XPT2046_asukiaaa_python-1.0.0.dist-info/top_level.txt
XPT2046_asukiaaa_python-1.0.0.dist-info/RECORD
