Metadata-Version: 2.1
Name: XPT2046-asukiaaa-python
Version: 1.0.0
Summary: A library to use XPT2046 touch module
Author-email: Asuki Kono <asukiaaa@gmail.com>
Project-URL: Homepage, https://github.com/asukiaaa/XPT2046_asukiaaa_python
Project-URL: Bug Tracker, https://github.com/asukiaaa/XPT2046_asukiaaa_python/issues
Project-URL: Repository, https://github.com/asukiaaa/XPT2046_asukiaaa_python.git
Keywords: spi,touch,xpt2046
Classifier: Programming Language :: Python :: 3
Classifier: License :: OSI Approved :: MIT License
Classifier: Operating System :: OS Independent
Requires-Python: >=3.7
License-File: LICENSE
Requires-Dist: adafruit-circuitpython-busdevice
